scaffold/cli.py
scaffold/generator.py
scaffold/git_utils.py
scaffold/templates/basic/.gitignore.j2
scaffold/templates/basic/README.md.j2
scaffold/templates/basic/main.py.j2
scaffold/templates/basic/pyproject.toml.j2
scaffold/templates/fastapi/.gitignore.j2
scaffold/templates/fastapi/README.md.j2
scaffold/templates/fastapi/main.py.j2
scaffold/templates/fastapi/pyproject.toml.j2
scaffold_cli_tool-0.2.0.dist-info/licenses/LICENSE
scaffold_cli_tool-0.2.0.dist-info/METADATA
scaffold_cli_tool-0.2.0.dist-info/WHEEL
scaffold_cli_tool-0.2.0.dist-info/top_level.txt
scaffold_cli_tool-0.2.0.dist-info/RECORD
