Metadata-Version: 2.4
Name: scaffold-cli-tool
Version: 0.2.0
Summary: A simple CLI tool to scaffold Python projects.
License-File: LICENSE
Requires-Dist: click
Requires-Dist: jinja2
Requires-Dist: rich
Requires-Dist: GitPython
Dynamic: license-file
